cvfe/__init__.py
cvfe/main.py
cvfe/api/__init__.py
cvfe/api/apps.py
cvfe/api/models.py
cvfe/api/convert/__init__.py
cvfe/api/convert/adobe_xfa.py
cvfe/configs/__init__.py
cvfe/configs/data/canada-country-code-to-name.csv
cvfe/configs/data/iran-province-to-city.csv
cvfe/convert/__init__.py
cvfe/convert/adobe_xfa.py
cvfe/data/__init__.py
cvfe/data/constant.py
cvfe/data/functional.py
cvfe/data/pdf.py
cvfe/data/preprocessor.py
cvfe/utils/__init__.py
cvfe/utils/import_utils.py
cvfe-1.1.0.dist-info/LICENSE
cvfe-1.1.0.dist-info/METADATA
cvfe-1.1.0.dist-info/WHEEL
cvfe-1.1.0.dist-info/top_level.txt
cvfe-1.1.0.dist-info/RECORD
