Metadata-Version: 2.1
Name: cvfe
Version: 1.1.0
Summary: Canada Visa Forms (5257e and 5645e) Extractor.
Author-email: Nikan Doosti <nikan.doosti@outlook.com>
License: GNU GENERAL PUBLIC LICENSE
Project-URL: Homepage, https://github.com/Nikronic/canada-visa-form-extraction
Keywords: visa,extractor,canada,5257e,5645e
Classifier: License :: OSI Approved :: GNU General Public License v3 (GPLv3)
Classifier: Programming Language :: Python
Classifier: Programming Language :: Python :: 3.10
Classifier: Development Status :: 4 - Beta
Classifier: Intended Audience :: Developers
Requires-Python: >=3.10.6
License-File: LICENSE
Requires-Dist: pip >=23.1.2
Requires-Dist: xmltodict >=0.13.0
Requires-Dist: pikepdf >=8.2.1
Requires-Dist: pypdf >=3.17.0
Requires-Dist: python-dateutil >=2.8.1
Provides-Extra: api
Requires-Dist: pydantic >=2.0.3 ; extra == 'api'
Requires-Dist: fastapi >=0.100.0 ; extra == 'api'
Requires-Dist: gunicorn >=21.2.0 ; extra == 'api'
Requires-Dist: uvicorn >=0.23.1 ; extra == 'api'
Requires-Dist: python-multipart >=0.0.6 ; extra == 'api'
Requires-Dist: pydantic-settings >=2.0.2 ; extra == 'api'
Requires-Dist: pyngrok >=6.0.0 ; extra == 'api'
Requires-Dist: requests >=2.31.0 ; extra == 'api'
Provides-Extra: doc
Requires-Dist: sphinx >=7.1.2 ; extra == 'doc'
Requires-Dist: sphinx-copybutton >=0.5.2 ; extra == 'doc'
Requires-Dist: sphinx-autodoc-typehints >=1.24.0 ; extra == 'doc'
Requires-Dist: myst-parser >=2.0.0 ; extra == 'doc'
Requires-Dist: furo >=2023.8.19 ; extra == 'doc'
Provides-Extra: format
Requires-Dist: pre-commit >=3.6.0 ; extra == 'format'
Provides-Extra: test
Requires-Dist: httpx >=0.24.1 ; extra == 'test'
Requires-Dist: pytest >=7.4.0 ; extra == 'test'
